README.rst
setup.cfg
setup.py
ummalqura/__init__.py
ummalqura/hijri.py
ummalqura/hijri_date.py
ummalqura/ummalqura_arrray.py
ummalqura.egg-info/PKG-INFO
ummalqura.egg-info/SOURCES.txt
ummalqura.egg-info/dependency_links.txt
ummalqura.egg-info/not-zip-safe
ummalqura.egg-info/top_level.txt