Metadata-Version: 1.0
Name: ummalqura
Version: 2.0.1
Summary: Python Hijri Ummalqura
Home-page: https://github.com/borni-dhifi/ummalqura
Author: Borni DHIFI
Author-email: dhifi.borni@gmail.com
License: Waqef
Keywords: ummalqura
Platform: UNKNOWN
